brigitte/__init__.py
brigitte/card.py
brigitte/deck.py
brigitte/game.py
brigitte/player.py
brigitte/commands/__init__.py
brigitte/commands/pile.py
brigitte_pkg_youszef-0.0.1.dist-info/LICENSE
brigitte_pkg_youszef-0.0.1.dist-info/METADATA
brigitte_pkg_youszef-0.0.1.dist-info/WHEEL
brigitte_pkg_youszef-0.0.1.dist-info/top_level.txt
brigitte_pkg_youszef-0.0.1.dist-info/RECORD
