Metadata-Version: 2.1
Name: brigitte-pkg-youszef
Version: 0.0.1
Summary: A Card Game
Home-page: https://github.com/youszef/brigitte-py
Author: Youszef
License: UNKNOWN
Platform: UNKNOWN
Classifier: Programming Language :: Python :: 3
Classifier: License :: OSI Approved :: BSD License
Classifier: Operating System :: OS Independent
Requires-Python: >=3.9
